annhub_python/__init__.py
annhub_python/application.py
annhub_python/core/__init__.py
annhub_python/core/errors.py
annhub_python/core/logging.py
annhub_python/ml_lib/__init__.py
annhub_python/ml_lib/annhub.pyd
annhub_python/model/__init__.py
annhub_python/model/prediction.py
annhub_python/routes.py
annhub_python/services/__init__.py
annhub_python/services/predict.py
annhub_python-0.1.6.dist-info/WHEEL
annhub_python-0.1.6.dist-info/METADATA
annhub_python-0.1.6.dist-info/RECORD
