Metadata-Version: 2.1
Name: annhub-python
Version: 0.1.6
Summary: Main backend module, which is used for developing web-app logic and deploying AI model.
Home-page: https://github.com/ans-ari/annhub-python
Author: ARI Technology
Author-email: dung.ut@ari.com.vn
Requires-Python: >=3.7,<4.0
Classifier: Operating System :: Microsoft :: Windows
Classifier: Programming Language :: Python :: 3
Classifier: Programming Language :: Python :: 3.7
Classifier: Programming Language :: Python :: 3.8
Classifier: Programming Language :: Python :: 3.9
Requires-Dist: fastapi (==0.68.1)
Requires-Dist: joblib (==1.0.1)
Requires-Dist: loguru (==0.4.0)
Requires-Dist: pydantic (>=1.8.2,<2.0.0)
Requires-Dist: pytest (==6.2.4)
Requires-Dist: requests (==2.22.0)
Requires-Dist: uvicorn (==0.11.1)
Project-URL: Repository, https://github.com/ans-ari/annhub-python
